{
	"info": {
		"_postman_id": "60a8d408-9e8b-4496-9d3f-d1ce6923ed94",
		"name": "Partical Task",
		"schema": "https://schema.getpostman.com/json/collection/v2.1.0/collection.json"
	},
	"item": [
		{
			"name": "Sign Up",
			"request": {
				"method": "GET",
				"header": []
			},
			"response": []
		},
		{
			"name": "Sign In",
			"request": {
				"method": "GET",
				"header": []
			},
			"response": []
		},
		{
			"name": "Search User",
			"request": {
				"method": "GET",
				"header": []
			},
			"response": []
		},
		{
			"name": "Send Friend Request",
			"request": {
				"method": "GET",
				"header": []
			},
			"response": []
		},
		{
			"name": "Update Friend Request Status",
			"request": {
				"method": "GET",
				"header": []
			},
			"response": []
		},
		{
			"name": "Accept Friend  Request",
			"request": {
				"method": "GET",
				"header": []
			},
			"response": []
		},
		{
			"name": "Pendig Friend Request",
			"request": {
				"method": "GET",
				"header": []
			},
			"response": []
		},
		{
			"name": "Reject Friend Request",
			"request": {
				"method": "GET",
				"header": []
			},
			"response": []
		}
	]
}